{"assets":{"6914580DE91874325D15F7CB61DB76CA":{"type":"texture","index":1,"assetRequest":{"type":"slide","state":"contents","slide":"none"},"url":{"native":"assets\/E7437A15-D878-4254-9EDC-04D568DD908C.pdf"},"width":1024,"height":768},"895BC6F9746D9E3A294D214E3F4F8290":{"type":"texture","index":0,"assetRequest":{"type":"slide","state":"contents","slide":"none"},"url":{"native":"assets\/E7437A15-D878-4254-9EDC-04D568DD908C.pdf"},"width":1024,"height":768}},"events":[{"effects":[{"beginTime":0,"baseLayer":{"animations":[],"initialState":{"affineTransform":[1,0,0,1,0,0],"masksToBounds":false,"rotation":0,"scale":1,"position":{"pointX":512,"pointY":384},"width":1024,"sublayerTransform":[1,0,0,0,0,1,0,0,0,0,1,0,0,0,0,1],"contentsRect":{"y":0,"x":0,"width":1,"height":1},"opacity":1,"edgeAntialiasingMask":251658240,"height":768,"hidden":false,"anchorPoint":{"pointX":0.5,"pointY":0.5}},"objectID":"0","layers":[{"animations":[],"initialState":{"affineTransform":[1,0,0,1,0,0],"masksToBounds":false,"rotation":0,"scale":1,"position":{"pointX":512,"pointY":384},"width":1024,"sublayerTransform":[1,0,0,0,0,1,0,0,0,0,1,-0.0004922987690640373,0,0,0,1],"contentsRect":{"y":0,"x":0,"width":1,"height":1},"opacity":1,"edgeAntialiasingMask":251658240,"height":768,"hidden":false,"anchorPoint":{"pointX":0.5,"pointY":0.5}},"layers":[{"animations":[],"layers":[],"texturedRectangle":{"isBackgroundTexture":false,"singleTextureOpacity":1,"textureType":0,"textBaseline":0,"textXHeight":0,"isVerticalText":false},"initialState":{"affineTransform":[1,0,0,1,0,0],"masksToBounds":false,"rotation":0,"scale":1,"position":{"pointX":512,"pointY":384},"width":1024,"sublayerTransform":[1,0,0,0,0,1,0,0,0,0,1,0,0,0,0,1],"contentsRect":{"y":0,"x":0,"width":1,"height":1},"opacity":1,"edgeAntialiasingMask":0,"height":768,"hidden":false,"anchorPoint":{"pointX":0.5,"pointY":0.5}},"texture":"6914580DE91874325D15F7CB61DB76CA"},{"animations":[{"timeOffset":0,"from":{"scalar":false},"beginTime":0,"repeatCount":0,"fillMode":"both","property":"hidden","autoreverses":false,"duration":0.01,"to":{"scalar":true}}],"layers":[],"texturedRectangle":{"isBackgroundTexture":false,"singleTextureOpacity":1,"textureType":0,"textBaseline":0,"textXHeight":0,"isVerticalText":false},"initialState":{"affineTransform":[1,0,0,1,0,0],"masksToBounds":false,"rotation":0,"scale":1,"position":{"pointX":512,"pointY":384},"width":1024,"sublayerTransform":[1,0,0,0,0,1,0,0,0,0,1,0,0,0,0,1],"contentsRect":{"y":0,"x":0,"width":1,"height":1},"opacity":1,"edgeAntialiasingMask":0,"height":768,"hidden":false,"anchorPoint":{"pointX":0.5,"pointY":0.5}},"texture":"895BC6F9746D9E3A294D214E3F4F8290"}]}]},"effects":[],"duration":0.01,"type":"transition","name":"none","objectID":"0"}],"automaticPlay":false,"hyperlinks":[],"accessibility":[{"text":"ASSISTANCE & ACCESSIBILITY","targetRectangle":{"y":29.14985930919647,"x":193.3549923706053,"width":637.2900000000004,"height":61}},{"text":"REQUEST FOR ASSISTANCE","targetRectangle":{"y":153.4361419677734,"x":116.0971322631836,"width":287.16,"height":110}},{"text":"Voters may have someone help them in the voting booth, but the voter and assistant must both sign a Request for Assistance form.","targetRectangle":{"y":277.4361419677734,"x":66.0598977804184,"width":386.58,"height":205}},{"text":"Exception: If the assistant chosen by the voter is age 15 or younger, neither the voter nor the assistant is required to complete the form.","targetRectangle":{"y":502.4361419677734,"x":66.0598977804184,"width":418.26,"height":205}},{"text":"LANGUAGE SERVICES","targetRectangle":{"y":155.4722595214844,"x":550.210234375,"width":424.5600000000001,"height":55}},{"text":"Language Officers","targetRectangle":{"y":224.4722595214844,"x":558.7629998922348,"width":251.1900000000001,"height":41}},{"text":"Phone translation line","targetRectangle":{"y":265.4722595214844,"x":558.7629998922348,"width":295.23,"height":41}},{"text":"All signs and documents in\\u20284 languages (English, Spanish, Vietnamese, and Korean)","targetRectangle":{"y":306.4722595214844,"x":558.7629998922348,"width":420.27,"height":123}},{"text":"VOTERS WITH DISABILITIES","targetRectangle":{"y":506.701416015625,"x":625.3102343749999,"width":284.3600000000001,"height":110}},{"text":"Be respectful!","targetRectangle":{"y":630.701416015625,"x":558.7629998922348,"width":188.88,"height":41}},{"text":"Always ask before assisting.","targetRectangle":{"y":671.701416015625,"x":558.7629998922348,"width":377.6099999999999,"height":41}}],"baseLayer":{"animations":[],"initialState":{"affineTransform":[1,0,0,1,0,0],"masksToBounds":false,"rotation":0,"scale":1,"position":{"pointX":512,"pointY":384},"width":1024,"sublayerTransform":[1,0,0,0,0,1,0,0,0,0,1,0,0,0,0,1],"contentsRect":{"y":0,"x":0,"width":1,"height":1},"opacity":1,"edgeAntialiasingMask":251658240,"height":768,"hidden":false,"anchorPoint":{"pointX":0.5,"pointY":0.5}},"objectID":"0","layers":[{"animations":[],"initialState":{"affineTransform":[1,0,0,1,0,0],"masksToBounds":false,"rotation":0,"scale":1,"position":{"pointX":512,"pointY":384},"width":1024,"sublayerTransform":[1,0,0,0,0,1,0,0,0,0,1,-0.0004922987690640373,0,0,0,1],"contentsRect":{"y":0,"x":0,"width":1,"height":1},"opacity":1,"edgeAntialiasingMask":251658240,"height":768,"hidden":false,"anchorPoint":{"pointX":0.5,"pointY":0.5}},"layers":[{"animations":[],"layers":[],"texturedRectangle":{"isBackgroundTexture":false,"singleTextureOpacity":1,"textureType":0,"textBaseline":0,"textXHeight":0,"isVerticalText":false},"initialState":{"affineTransform":[1,0,0,1,0,0],"masksToBounds":false,"rotation":0,"scale":1,"position":{"pointX":512,"pointY":384},"width":1024,"sublayerTransform":[1,0,0,0,0,1,0,0,0,0,1,0,0,0,0,1],"contentsRect":{"y":0,"x":0,"width":1,"height":1},"opacity":1,"edgeAntialiasingMask":0,"height":768,"hidden":false,"anchorPoint":{"pointX":0.5,"pointY":0.5}},"texture":"895BC6F9746D9E3A294D214E3F4F8290"}]}]}}]}